{"format":2,"version":"5.0.4","globals":"6f970bb3fd818c0086bb8745517713d8","files":{"route_py":{"hash":"2312a4ca4ef1c8946c489d2ca1d3a0b5","index":{"nums":[1,59,0,29,0,0,0],"html_filename":"route_py.html","relative_filename":"route.py"}},"__init___py":{"hash":"af9d0d0de0ea3b71d198bc63f1499a7d","index":{"nums":[1,0,0,0,0,0,0],"html_filename":"__init___py.html","relative_filename":"__init__.py"}},"gps_py":{"hash":"4cbfe5918e61a025faf57fa222e5ca6f","index":{"nums":[1,85,0,4,0,0,0],"html_filename":"gps_py.html","relative_filename":"gps.py"}},"tests___init___py":{"hash":"af9d0d0de0ea3b71d198bc63f1499a7d","index":{"nums":[1,0,0,0,0,0,0],"html_filename":"tests___init___py.html","relative_filename":"tests/__init__.py"}},"tests_test_gps_node_py":{"hash":"901d27c69290681cc57afbc08a748639","index":{"nums":[1,64,0,0,0,0,0],"html_filename":"tests_test_gps_node_py.html","relative_filename":"tests/test_gps_node.py"}},"tests_test_gps_route_py":{"hash":"de6e44581e083e4b37a351151cd2ca23","index":{"nums":[1,132,0,0,0,0,0],"html_filename":"tests_test_gps_route_py.html","relative_filename":"tests/test_gps_route.py"}},"validate_route_py":{"hash":"770ef552c3f6507ae4cc7928bdb49645","index":{"nums":[1,24,0,24,0,0,0],"html_filename":"validate_route_py.html","relative_filename":"validate_route.py"}}}}